lingq/cli.py
lingq/config.py
lingq/lingqhandler.py
lingq/log.py
lingq/utils.py
lingq/commands/add_timestamps.py
lingq/commands/get_courses.py
lingq/commands/get_images.py
lingq/commands/get_lesson.py
lingq/commands/get_lessons.py
lingq/commands/get_words.py
lingq/commands/merge.py
lingq/commands/mk_library_overview.py
lingq/commands/mk_markdown.py
lingq/commands/mk_yomitan.py
lingq/commands/patch.py
lingq/commands/post.py
lingq/commands/post_yt_playlist.py
lingq/commands/reindex.py
lingq/commands/replace.py
lingq/commands/resplit.py
lingq/commands/show.py
lingq/commands/sort.py
lingq/commands/stats.py
lingq/models/cards.py
lingq/models/collection.py
lingq/models/collection_v3.py
lingq/models/counter.py
lingq/models/hint.py
lingq/models/language.py
lingq/models/lesson_v3.py
lingq/models/my_collections.py
lingq/models/readings.py
lingq/models/transliteration.py
lingq-1.1.0.dist-info/METADATA
lingq-1.1.0.dist-info/WHEEL
lingq-1.1.0.dist-info/entry_points.txt
lingq-1.1.0.dist-info/top_level.txt
lingq-1.1.0.dist-info/RECORD
