Metadata-Version: 2.4
Name: lingq
Version: 1.1.0
Project-URL: Repository, https://github.com/daxida/lingq
Keywords: cli,lingq
Classifier: Development Status :: 4 - Beta
Classifier: Environment :: Console
Classifier: Operating System :: OS Independent
Classifier: License :: OSI Approved :: MIT License
Classifier: Programming Language :: Python :: 3.12
Classifier: Programming Language :: Python :: 3.13
Classifier: Programming Language :: Python :: 3.14
Classifier: Programming Language :: Python :: 3 :: Only
Classifier: Topic :: Education
Classifier: Topic :: Software Development :: Libraries
Requires-Python: >=3.12
Requires-Dist: aiohttp>=3.9.5
Requires-Dist: aiohttp_retry>=2.8.3
Requires-Dist: click==8.1.7
Requires-Dist: natsort==8.4.0
Requires-Dist: python-dotenv==1.0.1
Requires-Dist: yt_dlp==2025.10.22
Requires-Dist: pydantic
Requires-Dist: roman==4.2
Requires-Dist: Levenshtein
Requires-Dist: loguru
Requires-Dist: platformdirs
Provides-Extra: etc
Requires-Dist: beautifulsoup4==4.12.3; extra == "etc"
Requires-Dist: faster_whisper==1.0.2; extra == "etc"
Requires-Dist: requests==2.32.3; extra == "etc"
Requires-Dist: ruff==0.7.0; extra == "etc"
Requires-Dist: mypy; extra == "etc"
Requires-Dist: tqdm==4.66.4; extra == "etc"
Requires-Dist: gpt4All; extra == "etc"
Provides-Extra: test
Requires-Dist: pytest==8.2.1; extra == "test"
Requires-Dist: deepdiff; extra == "test"
Provides-Extra: docs
Requires-Dist: mkdocs; extra == "docs"
Requires-Dist: mkdocs-material; extra == "docs"
Requires-Dist: mkdocs-click; extra == "docs"
Provides-Extra: all
Requires-Dist: lingq[etc,test]; extra == "all"
